ghosted/__init__.py
ghosted/anomaly_injector.py
ghosted/data_blender.py
ghosted/data_generator.py
ghosted/generate_data_from_template.py
ghosted/noise_injector.py
ghosted/synth_dataframe.py
ghosted-1.0.2.dist-info/LICENSE
ghosted-1.0.2.dist-info/METADATA
ghosted-1.0.2.dist-info/WHEEL
ghosted-1.0.2.dist-info/top_level.txt
ghosted-1.0.2.dist-info/RECORD
