Metadata-Version: 2.1
Name: ghosted
Version: 1.0.2
Summary: A Python library for synthetic data generation, data blending, anomaly injection, and noise injection.
Home-page: https://github.com/awright813/ghosted
Author: Andrea Wright Morgan
Author-email: andreawright0813@gmail.com
Classifier: Programming Language :: Python :: 3
Classifier: License :: OSI Approved :: MIT License
Classifier: Operating System :: OS Independent
Requires-Python: >=3.12
License-File: LICENSE
Requires-Dist: copulas>=0.11.1
Requires-Dist: matplotlib>=3.9.2
Requires-Dist: numpy>=2.1.2
Requires-Dist: pandas>=2.2.3
Requires-Dist: pytest>=8.3.3
Requires-Dist: scipy>=1.14.1
Requires-Dist: seaborn>=0.13.2
Requires-Dist: setuptools>=75.2.0
